icland/__init__.py
icland/agent.py
icland/constants.py
icland/presets.py
icland/prop.py
icland/types.py
icland/renderer/renderer.py
icland/renderer/sdfs.py
icland/server/trajectory_poster.py
icland/server/trajectory_server.py
icland/server/static/icland.png
icland/server/static/placeholder.png
icland/server/templates/index.html
icland/world_gen/JITModel.py
icland/world_gen/XMLReader.py
icland/world_gen/converter.py
icland/world_gen/model_editing.py
icland/world_gen/tile_data.py
icland/world_gen/tilemap/data.xml
icland/world_gen/tilemap/ramp_1_2.png
icland/world_gen/tilemap/ramp_2_3.png
icland/world_gen/tilemap/ramp_3_4.png
icland/world_gen/tilemap/ramp_4_5.png
icland/world_gen/tilemap/ramp_5_6.png
icland/world_gen/tilemap/square_1.png
icland/world_gen/tilemap/square_2.png
icland/world_gen/tilemap/square_3.png
icland/world_gen/tilemap/square_4.png
icland/world_gen/tilemap/square_5.png
icland/world_gen/tilemap/square_6.png
icland/world_gen/tilemap/square_boundary_1.png
icland/world_gen/tilemap/square_boundary_2.png
icland/world_gen/tilemap/square_boundary_3.png
icland/world_gen/tilemap/square_boundary_4.png
icland/world_gen/tilemap/square_boundary_5.png
icland/world_gen/tilemap/square_boundary_6.png
icland/world_gen/tilemap/square_corner_1.png
icland/world_gen/tilemap/square_corner_2.png
icland/world_gen/tilemap/square_corner_3.png
icland/world_gen/tilemap/square_corner_4.png
icland/world_gen/tilemap/square_corner_5.png
icland/world_gen/tilemap/square_corner_6.png
icland/world_gen/tilemap/square_turn_1.png
icland/world_gen/tilemap/square_turn_2.png
icland/world_gen/tilemap/square_turn_3.png
icland/world_gen/tilemap/square_turn_4.png
icland/world_gen/tilemap/square_turn_5.png
icland/world_gen/tilemap/square_turn_6.png
icland/world_gen/tilemap/vramp_1_2.png
icland/world_gen/tilemap/vramp_1_3.png
icland/world_gen/tilemap/vramp_1_4.png
icland/world_gen/tilemap/vramp_1_5.png
icland/world_gen/tilemap/vramp_1_6.png
icland/world_gen/tilemap/vramp_2_3.png
icland-0.2.0.dist-info/METADATA
icland-0.2.0.dist-info/WHEEL
icland-0.2.0.dist-info/licenses/LICENSE
icland-0.2.0.dist-info/RECORD
