Metadata-Version: 2.4
Name: icland
Version: 0.2.0
Summary: Recreating Google DeepMind's XLand RL environment in JAX
License-File: LICENSE
Requires-Python: >=3.13
Requires-Dist: beartype>=0.19.0
Requires-Dist: brax>=0.12.1
Requires-Dist: flask-cors>=5.0.0
Requires-Dist: flask-socketio>=5.5.1
Requires-Dist: flask>=3.1.0
Requires-Dist: flax>=0.10.2
Requires-Dist: gputil>=1.4.0
Requires-Dist: hilbertcurve>=2
Requires-Dist: imageio[ffmpeg]>=2.37.0
Requires-Dist: jax>=0.5.0; sys_platform != 'linux'
Requires-Dist: jax[cuda12]>=0.5.0; sys_platform == 'linux'
Requires-Dist: jaxtyping>=0.2.37
Requires-Dist: matplotlib>=3.10.0
Requires-Dist: mujoco-mjx>=3.2.6
Requires-Dist: mujoco>=3.2.6
Requires-Dist: numpy-stl>=3.2.0
Requires-Dist: numpy>=2.2.2
Requires-Dist: opencv-python>=4.11.0.86
Requires-Dist: py-cpuinfo>=9.0.0
Requires-Dist: pygame>=2.6.1
Requires-Dist: pylatex>=1.4.2
Requires-Dist: pynvml>=12.0.0
Requires-Dist: requests>=2.32.3
Requires-Dist: scipy>=1.15.1
Requires-Dist: types-setuptools>=75.8.0.20250110
Requires-Dist: websocket-client>=1.8.0
